deserted/__init__.py
deserted/log.py
deserted/log_book.py
deserted/log_mp.py
deserted/log_v1.py
deserted/log_v2.py
deserted/log_v3.py
deserted/log_zero.py
deserted/multi_tasks_manager.py
deserted/runner_2.1.py
deserted/runner_3.1.py
deserted/ssh_manager.py
examples/__init__.py
test/__init__.py
test/argument.py
test/test_log.py
test/test_mail.py
tlib/__init__.py
tlib/cache.py
tlib/const.py
tlib/decorators.py
tlib/exceptions.py
tlib/version.py
tlib/aws/__init__.py
tlib/aws/boto3_api.py
tlib/aws/boto_api.py
tlib/bs/__init__.py
tlib/bs/bs.py
tlib/db/__init__.py
tlib/db/cassandra_api.py
tlib/db/etcd_api.py
tlib/db/pymysql_api.py
tlib/db/sqlite_api.py
tlib/docker/__init__.py
tlib/docker/docker_manager.py
tlib/ds/__init__.py
tlib/ds/ds.py
tlib/es/__init__.py
tlib/es/argument.py
tlib/es/elasticsearch_api.py
tlib/es/elasticsearch_index.py
tlib/es/elasticsearch_mock.py
tlib/es/elasticsearch_super.py
tlib/es/example_settings.py
tlib/es/index.py
tlib/es/index_stress.py
tlib/es/queries.py
tlib/es/test.py
tlib/fileop/__init__.py
tlib/fileop/fileops.py
tlib/fileop/lock_file.py
tlib/fileop/manage_file.py
tlib/git/__init__.py
tlib/git/git_manager.py
tlib/git/gitlab_api.py
tlib/jenkinslib/__init__.py
tlib/jenkinslib/internal/__init__.py
tlib/jenkinslib/internal/artifacts.py
tlib/jenkinslib/internal/base.py
tlib/jenkinslib/internal/build.py
tlib/jenkinslib/internal/exception.py
tlib/jenkinslib/internal/jenkins.py
tlib/jenkinslib/internal/job.py
tlib/jenkinslib/internal/jobs.py
tlib/jenkinslib/internal/label.py
tlib/jenkinslib/internal/node.py
tlib/jenkinslib/internal/nodes.py
tlib/jenkinslib/internal/promotion.py
tlib/jenkinslib/internal/promotion_build.py
tlib/jenkinslib/internal/promotions.py
tlib/jenkinslib/internal/queue.py
tlib/jenkinslib/internal/requester.py
tlib/jenkinslib/internal/utils.py
tlib/k8s/__init__.py
tlib/k8s/kubernetes_api.py
tlib/log/__init__.py
tlib/log/log.py
tlib/ltp/__init__.py
tlib/ltp/bd.py
tlib/ltp/filebench.py
tlib/mail/__init__.py
tlib/mail/mail.py
tlib-1.2.10.dist-info/LICENSE
tlib-1.2.10.dist-info/METADATA
tlib-1.2.10.dist-info/WHEEL
tlib-1.2.10.dist-info/top_level.txt
tlib-1.2.10.dist-info/RECORD
