Metadata-Version: 2.1
Name: tlib
Version: 1.2.10
Summary: Some own/observed great lib/ideas,common useful python libs
Home-page: https://github.com/txu2008/tlib
Author: tao.xu2008@outlook.com
Author-email: tao.xu2008@outlook.com
Maintainer: tao.xu2008@outlook.com
License: UNKNOWN
Keywords: library common baselib framework,stress runnner
Platform: UNKNOWN
Classifier: License :: OSI Approved :: MIT License
Classifier: Natural Language :: English
Classifier: Intended Audience :: Developers
Classifier: Operating System :: Microsoft :: Windows
Classifier: Operating System :: POSIX :: Linux
Classifier: Programming Language :: Python :: 2.7
Classifier: Programming Language :: Python :: 3
Classifier: Topic :: Software Development :: Libraries :: Python Modules
Classifier: Topic :: Utilities
Requires-Python: >=2.6
Requires-Dist: pyVmomi
Requires-Dist: superelasticsearch
Requires-Dist: elasticsearch
Requires-Dist: asn1crypto (==0.24.0)
Requires-Dist: bcrypt (==3.1.7)
Requires-Dist: bleach (==3.1.0)
Requires-Dist: certifi (==2019.6.16)
Requires-Dist: cffi (==1.12.3)
Requires-Dist: chardet (==3.0.4)
Requires-Dist: colorama (==0.4.1)
Requires-Dist: coloredlogs (==10.0)
Requires-Dist: cryptography (==2.7)
Requires-Dist: docutils (==0.15.2)
Requires-Dist: humanfriendly (==4.18)
Requires-Dist: idna (==2.8)
Requires-Dist: paramiko (==2.6.0)
Requires-Dist: pexpect (==4.7.0)
Requires-Dist: pkginfo (==1.5.0.1)
Requires-Dist: progressbar (==2.5)
Requires-Dist: ptyprocess (==0.6.0)
Requires-Dist: pycparser (==2.19)
Requires-Dist: Pygments (==2.4.2)
Requires-Dist: PyNaCl (==1.3.0)
Requires-Dist: pyreadline (==2.1)
Requires-Dist: PyYAML (==5.1.2)
Requires-Dist: readme-renderer (==24.0)
Requires-Dist: requests (==2.22.0)
Requires-Dist: requests-toolbelt (==0.9.1)
Requires-Dist: scp (==0.13.2)
Requires-Dist: six (==1.12.0)
Requires-Dist: tqdm (==4.32.2)
Requires-Dist: twine (==1.13.0)
Requires-Dist: urllib3 (==1.25.3)
Requires-Dist: webencodings (==0.5.1)
Requires-Dist: xlrd (==1.2.0)
